olaf/__init__.py
olaf/_version.py
olaf/_internals/__init__.py
olaf/_internals/app.py
olaf/_internals/updater.py
olaf/_internals/resources/__init__.py
olaf/_internals/resources/daemons.py
olaf/_internals/resources/ecss.py
olaf/_internals/resources/fread.py
olaf/_internals/resources/fwrite.py
olaf/_internals/resources/system.py
olaf/_internals/rest_api/__init__.py
olaf/_internals/rest_api/static/favicon.ico
olaf/_internals/rest_api/templates/_base.html
olaf/_internals/rest_api/templates/base.html
olaf/_internals/rest_api/templates/daemons.html
olaf/_internals/rest_api/templates/fread.html
olaf/_internals/rest_api/templates/fwrite.html
olaf/_internals/rest_api/templates/logs.html
olaf/_internals/rest_api/templates/od.html
olaf/_internals/rest_api/templates/os_command.html
olaf/_internals/rest_api/templates/reset.html
olaf/_internals/rest_api/templates/root.html
olaf/_internals/rest_api/templates/updater.html
olaf/_internals/services/__init__.py
olaf/_internals/services/logs.py
olaf/_internals/services/os_command.py
olaf/_internals/services/updater.py
olaf/board/adc.py
olaf/board/cpufreq.py
olaf/board/eeprom.py
olaf/board/gpio.py
olaf/board/pru.py
olaf/canopen/__init__.py
olaf/canopen/ecss.py
olaf/canopen/master_node.py
olaf/canopen/network.py
olaf/canopen/node.py
olaf/common/__init__.py
olaf/common/daemon.py
olaf/common/oresat_file.py
olaf/common/oresat_file_cache.py
olaf/common/resource.py
olaf/common/service.py
oresat_olaf-3.6.5.dist-info/licenses/LICENSE
oresat_olaf-3.6.5.dist-info/METADATA
oresat_olaf-3.6.5.dist-info/WHEEL
oresat_olaf-3.6.5.dist-info/top_level.txt
oresat_olaf-3.6.5.dist-info/RECORD
