Metadata-Version: 2.4
Name: oresat-olaf
Version: 3.6.5
Summary: Application framework for all OreSat Linux boards
License: GPL-3.0
Classifier: License :: OSI Approved :: GNU General Public License v3 (GPLv3)
Classifier: Operating System :: POSIX :: Linux
Classifier: Programming Language :: Python :: 3
Classifier: Programming Language :: Python :: 3.9
Classifier: Programming Language :: Python :: 3.10
Classifier: Programming Language :: Python :: 3.11
Classifier: Topic :: Software Development :: Embedded Systems
Classifier: Topic :: Software Development :: Libraries :: Application Frameworks
Requires-Python: >=3.9
License-File: LICENSE
Requires-Dist: canopen
Requires-Dist: flask
Requires-Dist: loguru
Requires-Dist: psutil
Requires-Dist: python-can>=4.3.0
Requires-Dist: oresat-configs<1.0.0
Dynamic: license-file
